emaildiff/__init__.py
emaildiff/maildiff_cmd.py
emaildiff/mail/__init__.py
emaildiff/mail/send.py
maildiff-2.0.0.data/data/VERSION
maildiff-2.0.0.data/scripts/git-maildiff
maildiff-2.0.0.dist-info/LICENSE
maildiff-2.0.0.dist-info/METADATA
maildiff-2.0.0.dist-info/WHEEL
maildiff-2.0.0.dist-info/entry_points.txt
maildiff-2.0.0.dist-info/top_level.txt
maildiff-2.0.0.dist-info/RECORD
