Metadata-Version: 2.1
Name: maildiff
Version: 2.0.0
Summary: Package to email color git diff
Home-page: https://github.com/sanfx/git-maildiff
Author: Sanjeev Kumar
Author-email: sansupercool@duck.com
License: BSD
Platform: Unix
Platform: Darwin
Platform: Windows
Classifier: Development Status :: 5 - Production/Stable
Classifier: Environment :: Console
Classifier: Intended Audience :: Developers
Classifier: Intended Audience :: System Administrators
Classifier: License :: OSI Approved :: BSD License
Classifier: Operating System :: Unix
Classifier: Programming Language :: Python
Classifier: Programming Language :: Python :: 3
Classifier: Programming Language :: Python :: 3.3
Classifier: Programming Language :: Python :: 3.4
Classifier: Programming Language :: Python :: 3.7
Classifier: Topic :: Software Development
Classifier: Topic :: Software Development :: Version Control
Classifier: Topic :: Utilities
License-File: LICENSE
Requires-Dist: keyring >=5.3
Requires-Dist: colorlog >=2.6.0
